databuri/__init__.py
databuri/configuration.py
databuri/logger.py
databuri/datasources/__init__.py
databuri/datasources/air4thai.py
databuri/datasources/govspending.py
databuri-0.1.0.dev0.dist-info/LICENSE
databuri-0.1.0.dev0.dist-info/METADATA
databuri-0.1.0.dev0.dist-info/WHEEL
databuri-0.1.0.dev0.dist-info/top_level.txt
databuri-0.1.0.dev0.dist-info/RECORD
